pptrees/AdderForest.py
pptrees/AdderTree.py
pptrees/EquivClass.py
pptrees/ExpressionForest.py
pptrees/ExpressionGraph.py
pptrees/ExpressionNode.py
pptrees/ExpressionTree.py
pptrees/YosysAdder.py
pptrees/__init__.py
pptrees/adder_tree.py
pptrees/util.py
pptrees/yosys_alu.py
pptrees/mappings/GTECH_map.v
pptrees/mappings/__init__.py
pptrees/mappings/asap7sc7p5t_28_R.v
pptrees/mappings/behavioral_map.v
pptrees/mappings/sky130_fd_sc_hd_map.v
pptrees/mappings/sky130_fd_sc_hs_map.v
pptrees/mappings/sky130_fd_sc_ls_map.v
pptrees/mappings/sky130_fd_sc_ms_map.v
pptrees/node_data/__init__.py
pptrees/node_data/invis.py
pptrees/node_data/ppa_buffer.py
pptrees/node_data/ppa_cocycle.py
pptrees/node_data/ppa_lspine.py
pptrees/node_data/ppa_lspine_pre.py
pptrees/node_data/ppa_lspine_pre_simple.py
pptrees/node_data/ppa_lspine_single.py
pptrees/node_data/ppa_post.py
pptrees/node_data/ppa_post_nolspine.py
pptrees/node_data/ppa_post_plusone.py
pptrees/node_data/ppa_pre.py
pptrees/node_data/ppa_pre_t.py
pptrees/node_data/ppa_rspine.py
pptrees/node_data/ppa_rspine_buffer.py
pptrees/node_data/ppa_rspine_pre.py
pptrees/node_data/ppa_small_root.py
pptrees-1.3.6.dist-info/LICENSE
pptrees-1.3.6.dist-info/METADATA
pptrees-1.3.6.dist-info/WHEEL
pptrees-1.3.6.dist-info/top_level.txt
pptrees-1.3.6.dist-info/RECORD
