Metadata-Version: 2.1
Name: pptrees
Version: 1.3.6
Summary: Parallel Prefix tree generation library
Home-page: https://github.com/tdene/synth_opt_adders
Author: tdene
Author-email: teodord.ene@gmail.com
License: Apache 2.0
Keywords: hardware adders prefix
Classifier: Development Status :: 3 - Alpha
Classifier: Topic :: System :: Hardware
Classifier: License :: OSI Approved :: Apache Software License
Classifier: Programming Language :: Python :: 3
Requires-Python: >=3.6.*
License-File: LICENSE
Requires-Dist: networkx
Requires-Dist: pydot
Requires-Dist: graphviz
Requires-Dist: Pillow
Requires-Dist: importlib-resources ; python_version == "3.6"
